README.md
setup.cfg
setup.py
PyImp.egg-info/PKG-INFO
PyImp.egg-info/SOURCES.txt
PyImp.egg-info/dependency_links.txt
PyImp.egg-info/entry_points.txt
PyImp.egg-info/requires.txt
PyImp.egg-info/top_level.txt
pimp/__init__.py
pimp/__version__.py
pimp/pimp.py
pimp/configspace/__init__.py
pimp/epm/__init__.py
pimp/epm/base_epm.py
pimp/epm/epar_x_rfwi.py
pimp/epm/unlogged_epar_x_rfwi.py
pimp/epm/unlogged_rfwi.py
pimp/evaluator/__init__.py
pimp/evaluator/ablation.py
pimp/evaluator/base_evaluator.py
pimp/evaluator/fanova.py
pimp/evaluator/forward_selection.py
pimp/evaluator/influence_models.py
pimp/evaluator/local_parameter_importance.py
pimp/importance/__init__.py
pimp/importance/importance.py
pimp/utils/__init__.py
pimp/utils/bokeh_helpers.py
pimp/utils/tex.py
pimp/utils/io/__init__.py
pimp/utils/io/cmd_reader.py