Metadata-Version: 1.1
Name: PyImp
Version: 1.1.1
Summary: Package for automated Parameter Importance Analysis after Configuration.
Home-page: UNKNOWN
Author: biedenka
Author-email: biedenka@cs.uni-freiburg.de
License: BSD 3-clause
Platform: Linux
Classifier: Development Status :: 4 - Beta
Classifier: Topic :: Utilities
Classifier: Topic :: Scientific/Engineering
Classifier: Topic :: Scientific/Engineering :: Artificial Intelligence
Classifier: Topic :: Scientific/Engineering :: Information Analysis
Classifier: Topic :: Scientific/Engineering :: Visualization
Classifier: License :: OSI Approved :: BSD License
Classifier: Intended Audience :: Science/Research
Classifier: Intended Audience :: Developers
Classifier: Intended Audience :: Education
